persistence.py
mindpowered_sqlalchemy_persistence/Persistence.py
mindpowered_sqlalchemy_persistence/__init__.py
mindpowered_sqlalchemy_persistence-0.0.7.dist-info/LICENSE.txt
mindpowered_sqlalchemy_persistence-0.0.7.dist-info/METADATA
mindpowered_sqlalchemy_persistence-0.0.7.dist-info/WHEEL
mindpowered_sqlalchemy_persistence-0.0.7.dist-info/top_level.txt
mindpowered_sqlalchemy_persistence-0.0.7.dist-info/RECORD
